ggwave_python/__init__.py
ggwave_python/ggwave.py
ggwave_python/optionals.py
ggwave_python/wav_utils.py
ggwave_python/waveform_utils.py
ggwave_python-0.1.11.dist-info/LICENSE
ggwave_python-0.1.11.dist-info/METADATA
ggwave_python-0.1.11.dist-info/WHEEL
ggwave_python-0.1.11.dist-info/RECORD
