Metadata-Version: 2.3
Name: ggwave_python
Version: 0.1.11
Summary: A Python wrapper for GGWave – data-over-sound communication
License: MIT
Author: Abzac
Author-email: rapturec@gmail.com
Requires-Python: >=3.8, !=2.7.*, !=3.0.*, !=3.1.*, !=3.2.*, !=3.3.*, !=3.4.*, !=3.5.*, !=3.6.*, !=3.7.*, !=3.11.*, !=3.12.*, !=3.13.*
Classifier: Development Status :: 4 - Beta
Classifier: Intended Audience :: Developers
Classifier: License :: OSI Approved :: MIT License
Classifier: Operating System :: OS Independent
Classifier: Programming Language :: Python :: 3
Classifier: Programming Language :: Python :: 3.8
Classifier: Programming Language :: Python :: 3.10
Classifier: Programming Language :: Python :: 3.9
Classifier: Topic :: Software Development :: Libraries :: Python Modules
Provides-Extra: audio
Requires-Dist: cryptography (>=44.0.1)
Requires-Dist: ggwave (>=0.4.2,<0.5.0)
Requires-Dist: numpy (>=1.22.0) ; extra == "audio"
Requires-Dist: pyaudio (>=0.2.14,<0.3.0) ; extra == "audio"
Project-URL: Bug Tracker, https://github.com/Abzac/ggwave-python/issues
Project-URL: Documentation, https://github.com/Abzac/ggwave-python/wiki
Project-URL: Source Code, https://github.com/Abzac/ggwave-python
